udata/__init__.py
udata/api_fields.py
udata/app.py
udata/cors.py
udata/errors.py
udata/factories.py
udata/i18n.py
udata/mail.py
udata/rdf.py
udata/routing.py
udata/sentry.py
udata/settings.py
udata/sitemap.py
udata/tags.py
udata/tasks.py
udata/tracking.py
udata/uris.py
udata/utils.py
udata/worker.py
udata/wsgi.py
udata/api/__init__.py
udata/api/commands.py
udata/api/errors.py
udata/api/fields.py
udata/api/oauth2.py
udata/api/parsers.py
udata/api/signals.py
udata/auth/__init__.py
udata/auth/forms.py
udata/auth/helpers.py
udata/auth/mails.py
udata/auth/password_validation.py
udata/auth/proconnect.py
udata/auth/views.py
udata/commands/__init__.py
udata/commands/cache.py
udata/commands/db.py
udata/commands/dcat.py
udata/commands/fixtures.py
udata/commands/images.py
udata/commands/info.py
udata/commands/init.py
udata/commands/purge.py
udata/commands/serve.py
udata/commands/test.py
udata/commands/worker.py
udata/commands/tests/__init__.py
udata/commands/tests/test_fixtures.py
udata/core/__init__.py
udata/core/captchetat.py
udata/core/constants.py
udata/core/csv.py
udata/core/linkable.py
udata/core/owned.py
udata/core/access_type/api.py
udata/core/access_type/constants.py
udata/core/access_type/models.py
udata/core/activity/__init__.py
udata/core/activity/api.py
udata/core/activity/models.py
udata/core/activity/signals.py
udata/core/activity/tasks.py
udata/core/avatars/api.py
udata/core/avatars/test_avatar_api.py
udata/core/badges/__init__.py
udata/core/badges/api.py
udata/core/badges/commands.py
udata/core/badges/factories.py
udata/core/badges/fields.py
udata/core/badges/forms.py
udata/core/badges/models.py
udata/core/badges/permissions.py
udata/core/badges/signals.py
udata/core/badges/tasks.py
udata/core/badges/tests/__init__.py
udata/core/badges/tests/test_commands.py
udata/core/badges/tests/test_model.py
udata/core/badges/tests/test_tasks.py
udata/core/contact_point/__init__.py
udata/core/contact_point/api.py
udata/core/contact_point/api_fields.py
udata-14.10.0.dist-info/licenses/LICENSE
udata-14.10.0.dist-info/METADATA
udata-14.10.0.dist-info/WHEEL
udata-14.10.0.dist-info/entry_points.txt
udata-14.10.0.dist-info/top_level.txt
udata-14.10.0.dist-info/RECORD
